{
  "name": "Armand Malfoy",
  "gender": "Male",
  "born": "Pre 1066, France",
  "died": "Post 1066, England, Great Britain",
  "species": "Human",
  "height": null,
  "weight": null,
  "hair_color": null,
  "eye_color": null,
  "skin_color": null,
  "blood_status": "Pure-blood",
  "marital_status": null,
  "nationality": "French/English",
  "animagus": null,
  "boggart": null,
  "house": null,
  "patronus": null,
  "alias_names": null,
  "jobs": null,
  "titles": null,
  "family_members": [
    "Nicholas Malfoy (descendant) †",
    "Lucius Malfoy I (descendant) †",
    "Brutus Malfoy (descendant) †",
    "Septimus Malfoy (descendant) †",
    "Abraxas Malfoy (descendant) †",
    "Lucius Malfoy II (descendant)",
    "Draco Malfoy (descendant)",
    "Scorpius Malfoy (descendant)",
    "Malfoy family"
  ],
  "romances": null,
  "wands": null,
  "image": "https://static.wikia.nocookie.net/harrypotter/images/2/2c/ArmandMalfoy.png",
  "wiki": "https://harrypotter.fandom.com/wiki/Armand_Malfoy"
}