{
  "name": "Gruffyd Wellnelly",
  "gender": "Male",
  "born": null,
  "died": null,
  "species": "Human",
  "height": null,
  "weight": null,
  "hair_color": "Brown",
  "eye_color": "Brown",
  "skin_color": "Light",
  "blood_status": null,
  "marital_status": null,
  "nationality": null,
  "animagus": null,
  "boggart": null,
  "house": "Gryffindor, Hufflepuff, or Slytherin",
  "patronus": null,
  "alias_names": [
    "Gruff (by Baglan Wellnelly)"
  ],
  "jobs": null,
  "titles": [
    "Seeker"
  ],
  "family_members": [
    "Dai Llewellyn (ancestor, possibly)",
    "Baglan Wellnelly (twin brother)",
    "Wellnelly family"
  ],
  "romances": null,
  "wands": null,
  "image": "https://static.wikia.nocookie.net/harrypotter/images/5/5d/Gruffyd_Wellnelly_HM.png",
  "wiki": "https://harrypotter.fandom.com/wiki/Gruffyd_Wellnelly"
}