{
  "name": "Mr Bigglesby",
  "gender": "Male",
  "born": "Before or in 1990–1991 school year",
  "died": null,
  "species": "Puffskein",
  "height": null,
  "weight": null,
  "hair_color": null,
  "eye_color": null,
  "skin_color": null,
  "blood_status": null,
  "marital_status": null,
  "nationality": null,
  "animagus": null,
  "boggart": null,
  "house": null,
  "patronus": null,
  "alias_names": null,
  "jobs": null,
  "titles": null,
  "family_members": null,
  "romances": null,
  "wands": null,
  "image": "https://static.wikia.nocookie.net/harrypotter/images/4/48/The_Ghost%27s_Puffskein_icon_HM.png",
  "wiki": "https://harrypotter.fandom.com/wiki/Mr_Bigglesby"
}