{
  "name": "Phillipus Aureolus Theophrastus Bombastus von Hohenheim",
  "gender": "Male",
  "born": "1493",
  "died": "1541 (aged 47-48)",
  "species": "Human",
  "height": null,
  "weight": null,
  "hair_color": "White",
  "eye_color": "Blue",
  "skin_color": "White",
  "blood_status": null,
  "marital_status": null,
  "nationality": null,
  "animagus": null,
  "boggart": null,
  "house": null,
  "patronus": null,
  "alias_names": [
    "Paracelsus"
  ],
  "jobs": [
    "Alchemist",
    "Physician"
  ],
  "titles": null,
  "family_members": null,
  "romances": null,
  "wands": null,
  "image": "https://static.wikia.nocookie.net/harrypotter/images/e/ec/Paracelsus_Chocolate_Frog_Card_%28WWHP%29.png",
  "wiki": "https://harrypotter.fandom.com/wiki/Phillipus_von_Hohenheim"
}