{
  "name": "Unidentified children in the MACUSA headquarters",
  "gender": "Males and Females",
  "born": "Before 1926",
  "died": null,
  "species": "Humans",
  "height": null,
  "weight": null,
  "hair_color": null,
  "eye_color": null,
  "skin_color": "Light",
  "blood_status": null,
  "marital_status": null,
  "nationality": null,
  "animagus": null,
  "boggart": null,
  "house": null,
  "patronus": null,
  "alias_names": null,
  "jobs": null,
  "titles": null,
  "family_members": null,
  "romances": null,
  "wands": null,
  "image": "https://static.wikia.nocookie.net/harrypotter/images/9/9a/Children_in_MACUSA_headquarters_FBF.png",
  "wiki": "https://harrypotter.fandom.com/wiki/Unidentified_children_in_the_MACUSA_headquarters"
}