{
  "name": "King William I",
  "gender": "Male",
  "born": "c. 1028",
  "died": "9 September 1087 (aged 58 or 59)",
  "species": "Human",
  "height": null,
  "weight": null,
  "hair_color": null,
  "eye_color": null,
  "skin_color": "Light",
  "blood_status": "Muggle",
  "marital_status": null,
  "nationality": null,
  "animagus": null,
  "boggart": null,
  "house": null,
  "patronus": null,
  "alias_names": [
    "William the Conqueror"
  ],
  "jobs": null,
  "titles": [
    "King of England",
    "Duke of Normandy"
  ],
  "family_members": null,
  "romances": null,
  "wands": null,
  "image": null,
  "wiki": "https://harrypotter.fandom.com/wiki/William_I"
}